linode_metadata/__init__.py
linode_metadata/constants.py
linode_metadata/metadata_client.py
linode_metadata/version.py
linode_metadata/watcher.py
linode_metadata/objects/__init__.py
linode_metadata/objects/error.py
linode_metadata/objects/instance.py
linode_metadata/objects/networking.py
linode_metadata/objects/response_base.py
linode_metadata/objects/ssh_keys.py
linode_metadata/objects/token.py
lgarber_fork_linode_metadata-0.2.0.dist-info/LICENSE
lgarber_fork_linode_metadata-0.2.0.dist-info/METADATA
lgarber_fork_linode_metadata-0.2.0.dist-info/WHEEL
lgarber_fork_linode_metadata-0.2.0.dist-info/top_level.txt
lgarber_fork_linode_metadata-0.2.0.dist-info/RECORD
