Metadata-Version: 2.1
Name: lgarber_fork_linode_metadata
Version: 0.2.0
Summary: A client to interact with the Linode Metadata service in Python.
Author-email: Linode <developers@linode.com>
License: BSD-3-Clause
Project-URL: homepage, https://github.com/linode/py-metadata
Project-URL: repository, https://github.com/linode/py-metadata.git
Classifier: Development Status :: 4 - Beta
Classifier: Intended Audience :: Developers
Classifier: Topic :: Software Development :: Libraries
Classifier: License :: OSI Approved :: BSD License
Classifier: Programming Language :: Python
Classifier: Programming Language :: Python :: 3
Classifier: Programming Language :: Python :: 3.8
Classifier: Programming Language :: Python :: 3.9
Classifier: Programming Language :: Python :: 3.10
Classifier: Programming Language :: Python :: 3.11
Classifier: Programming Language :: Python :: 3.12
Requires-Python: >=3.8
License-File: LICENSE
Requires-Dist: httpx
Provides-Extra: dev
Requires-Dist: pytest; extra == "dev"
Requires-Dist: black; extra == "dev"
Requires-Dist: isort; extra == "dev"
Requires-Dist: pylint; extra == "dev"
Requires-Dist: autoflake; extra == "dev"
Requires-Dist: Sphinx>=7.2.6; extra == "dev"
Requires-Dist: pytest-asyncio; extra == "dev"
Requires-Dist: sphinx-lint; extra == "dev"
Provides-Extra: doc
Requires-Dist: Sphinx>=7.2.6; extra == "doc"
